watchr_sdk/__init__.py
watchr_sdk-0.0.0.dist-info/METADATA
watchr_sdk-0.0.0.dist-info/WHEEL
watchr_sdk-0.0.0.dist-info/licenses/LICENSE.txt
watchr_sdk-0.0.0.dist-info/RECORD
