Metadata-Version: 2.1
Name: watchr-sdk
Version: 0.0.0
Summary: Watchr Python SDK
Project-URL: Documentation, https://github.com/getwatchr/watchr-python#readme
Project-URL: Issues, https://github.com/getwatchr/watchr-python/issues
Project-URL: Source, https://github.com/getwatchr/watchr-python
Author-email: Amin Alaee <me@aminalaee.dev>
License-Expression: MIT
License-File: LICENSE.txt
Classifier: Development Status :: 4 - Beta
Classifier: Programming Language :: Python
Classifier: Programming Language :: Python :: 3.7
Classifier: Programming Language :: Python :: 3.8
Classifier: Programming Language :: Python :: 3.9
Classifier: Programming Language :: Python :: 3.10
Classifier: Programming Language :: Python :: 3.11
Classifier: Programming Language :: Python :: Implementation :: CPython
Classifier: Programming Language :: Python :: Implementation :: PyPy
Requires-Python: >=3.7
Requires-Dist: httpx
